api/__init__.py
api/actor_tokens/__init__.py
api/actor_tokens/create_actor_token.py
api/actor_tokens/revoke_actor_token.py
api/allow_list_block_list/__init__.py
api/allow_list_block_list/create_allowlist_identifier.py
api/allow_list_block_list/create_blocklist_identifier.py
api/allow_list_block_list/delete_allowlist_identifier.py
api/allow_list_block_list/delete_blocklist_identifier.py
api/allow_list_block_list/list_allowlist_identifiers.py
api/allow_list_block_list/list_blocklist_identifiers.py
api/beta_features/__init__.py
api/beta_features/change_production_instance_domain.py
api/beta_features/update_instance_auth_config.py
api/beta_features/update_production_instance_domain.py
api/clients/__init__.py
api/clients/get_client.py
api/clients/get_client_last_active_session.py
api/clients/get_client_list.py
api/clients/verify_client.py
api/domains/__init__.py
api/domains/delete_domain.py
api/domains/list_domains.py
api/domains/update_domain.py
api/email_addresses/__init__.py
api/email_addresses/create_email_address.py
api/email_addresses/delete_email_address.py
api/email_addresses/get_email_address.py
api/email_addresses/update_email_address.py
api/email_sms_templates/__init__.py
api/email_sms_templates/get_template.py
api/email_sms_templates/get_template_list.py
api/email_sms_templates/preview_template.py
api/email_sms_templates/revert_template.py
api/email_sms_templates/upsert_template.py
api/emails/__init__.py
api/emails/create_email.py
api/instance_settings/__init__.py
api/instance_settings/update_instance.py
api/instance_settings/update_instance_organization_settings.py
api/instance_settings/update_instance_restrictions.py
api/invitations/__init__.py
api/invitations/create_invitation.py
api/invitations/list_invitations.py
api/jwks/__init__.py
api/jwks/get_jwks.py
api/jwt_templates/__init__.py
api/jwt_templates/create_jwt_template.py
api/jwt_templates/delete_jwt_template.py
api/jwt_templates/get_jwt_template.py
api/jwt_templates/list_jwt_templates.py
clerk_autogenerated_client-0.0.3.dist-info/METADATA
clerk_autogenerated_client-0.0.3.dist-info/WHEEL
clerk_autogenerated_client-0.0.3.dist-info/top_level.txt
clerk_autogenerated_client-0.0.3.dist-info/RECORD
