Metadata-Version: 2.1
Name: clerk_autogenerated_client
Version: 0.0.3
Summary: A client library for accessing Clerk Backend API
Author: Kuldeep
Author-email: kuldeep@liv.place
